compositional_attention_pytorch/__init__.py
compositional_attention_pytorch/compositional_attention_pytorch.py
compositional_attention_pytorch-0.0.1.dist-info/LICENSE
compositional_attention_pytorch-0.0.1.dist-info/METADATA
compositional_attention_pytorch-0.0.1.dist-info/WHEEL
compositional_attention_pytorch-0.0.1.dist-info/top_level.txt
compositional_attention_pytorch-0.0.1.dist-info/RECORD
